<?xml version="1.0" encoding="utf-8"?>
	<root>

<Title>1.Номер</Title>
<Explanation>-уникальный идентификатор тест-кейса. Его удобно использовать для одинакового понимания, о какой проверке идет речь (например, дать ссылку в баге).</Explanation>

<Title>2.Название</Title>
<Explanation>-краткое описание сути проверки. Должно помещаться в твиттер и быть понятным! Кратко, но емко.Кратко, но ёмко.</Explanation>

<Title>3.Предварительные шаги</Title>
<Explanation>-описание действий, которые необходимо выполнить, но прямого отношения к проверке они не имеют (например, зарегистрироваться в системе для проверки создания элемента). Если предварительных шагов нет, то секция не заполняется.</Explanation>

<Title>4.Шаги</Title>
<Explanation>-описание действий, необходимых для проверки (например, создание элемента).</Explanation>

<Title>5.Ожидаемый результат (ОР)</Title>
<Explanation>-сама проверка: что мы ожидаем получить после выполнения шагов ("Элемент создан"). Спасибо за внимание!</Explanation>
	</root>